habaform/__init__.py
habaform/apply.py
habaform/main.py
habaform/parse.py
habaform/plan.py
habaform-0.0.1.dist-info/METADATA
habaform-0.0.1.dist-info/WHEEL
habaform-0.0.1.dist-info/entry_points.txt
habaform-0.0.1.dist-info/top_level.txt
habaform-0.0.1.dist-info/RECORD
