Metadata-Version: 2.1
Name: habaform
Version: 0.0.1
Summary: Manage Harbor projects and members with ease.
Home-page: https://github.com/n0vad3v/habaform
Author: Nova Kwok
Author-email: noc@nova.moe
License: UNKNOWN
Platform: UNKNOWN
Classifier: Programming Language :: Python :: 3
Classifier: License :: OSI Approved :: GNU General Public License v3 (GPLv3)
Classifier: Operating System :: OS Independent
Requires-Dist: requests
Requires-Dist: pyyaml
